{
  "npcName": "first-npc",
  "animLookup": {
    "idle": {
      "animName": "idle",
      "aabb": {"x": 1, "y": 0, "width": 128, "height": 128},
      "frames": [
        [
          {
            "tags": ["leg-l"],
            "style": {
              "fill-opacity": "0.5",
              "stroke": "rgb(0, 0, 0)",
              "stroke-opacity": "0.5",
              "stroke-width": "0.5px",
              "fill": "rgb(85, 85, 85)",
              "pointer-events": "none"
            },
            "tagName": "path",
            "d": "M 60 44.8 L 60 64.2 L 40.569 64.094 L 40.464 44.726 L 60 44.8 Z"
          },
          {
            "tags": ["leg-r"],
            "style": {
              "fill-opacity": "0.5",
              "stroke": "rgb(0, 0, 0)",
              "stroke-opacity": "0.5",
              "stroke-width": "0.5px",
              "pointer-events": "none",
              "fill": "rgb(85, 85, 85)"
            },
            "tagName": "path",
            "d": "M 60 63.8 L 60 83.2 L 40.569 83.094 L 40.464 63.726 L 60 63.8 Z"
          },
          {
            "tags": ["arm-l"],
            "style": {
              "stroke": "rgb(0, 0, 0)",
              "stroke-opacity": "0.5",
              "stroke-width": "0.5px",
              "fill": "rgb(0, 0, 255)",
              "pointer-events": "none"
            },
            "tagName": "path",
            "d": "M 73.757 27.592 C 77.488 33.379 73.687 40.059 71.654 40.059 C 69.621 40.059 42.563 45.526 42.563 40.897 C 42.563 38.575 48.41 31.536 52.168 28.766 C 55.903 26.014 61.447 25.498 62.46 25.498 C 63.391 25.498 70.604 22.702 73.757 27.592 Z"
          },
          {
            "tags": ["arm-r"],
            "style": {
              "stroke": "rgb(0, 0, 0)",
              "stroke-opacity": "0.5",
              "stroke-width": "0.5px",
              "fill": "rgb(0, 0, 255)",
              "pointer-events": "none"
            },
            "tagName": "path",
            "d": "M 73.757 98.868 C 77.488 93.081 73.687 86.401 71.654 86.401 C 69.621 86.401 42.563 80.934 42.563 85.563 C 42.563 87.885 48.41 94.924 52.168 97.694 C 55.903 100.446 61.447 100.962 62.46 100.962 C 63.391 100.962 70.604 103.758 73.757 98.868 Z"
          },
          {
            "tags": ["chest"],
            "transform": [
              0.01447,
              0.999895,
              -0.999895,
              0.01447,
              121.633866,
              2.25406
            ],
            "style": {
              "stroke": "rgb(0, 0, 0)",
              "stroke-width": "0.5px",
              "fill-opacity": "0.6",
              "pointer-events": "none"
            },
            "tagName": "path",
            "d": "M 80.075 74.799 C 70.043 83.088 51.376 82.024 41.04 74.116 C 34.966 69.469 32.911 53.997 34.653 52.08 C 39.876 46.332 46.16 45.915 46.16 45.915 C 46.16 45.915 56.074 44.754 61.102 44.935 C 66.859 45.142 78.137 47.856 78.137 47.856 C 78.137 47.856 80.794 48.058 84.152 51.354 C 85.779 52.95 86.19 69.746 80.075 74.799 Z"
          },
          {
            "tags": ["shoulders"],
            "transform": [
              0.996287,
              -0.086089,
              0.086089,
              0.996287,
              -4.280137,
              5.791421
            ],
            "style": {
              "stroke": "rgb(0, 0, 0)",
              "pointer-events": "none",
              "fill-opacity": "0.8"
            },
            "tagName": "path",
            "d": "M 71.193 45.781 C 69.548 47.998 67.392 68.574 68.64 82.936 C 68.823 85.04 69.426 91.476 69.032 93.334 C 67.512 100.5 64.866 101.625 60.057 101.209 C 49.367 100.284 43.193 90.748 39.398 84.544 C 35.603 78.34 40.237 47.595 41.122 43.481 C 42.481 37.165 53.855 23.986 61.01 23.986 C 67.733 23.986 67.432 24.652 71.794 26.234 C 76.128 27.806 72.962 43.397 71.193 45.781 Z"
          },
          {
            "tags": ["head"],
            "transform": [-1, 0, 0, -1, 0, 0],
            "style": {
              "fill-opacity": "0.5",
              "stroke": "rgb(0, 0, 0)",
              "fill": "rgb(244, 212, 255)",
              "stroke-width": "0.25px",
              "pointer-events": "none"
            },
            "tagName": "ellipse",
            "cx": -66.745,
            "cy": -63.901,
            "rx": 14.49,
            "ry": 14.792
          },
          {
            "tags": ["hair"],
            "transform": [-1, 0, 0, -1, 129.848003, 127.802002],
            "style": {
              "fill-opacity": "0.5",
              "stroke": "rgb(0, 0, 0)",
              "stroke-width": "0.25px",
              "pointer-events": "none"
            },
            "tagName": "path",
            "d": "M 77.593 63.901 C 77.593 72.07 71.106 78.693 63.103 78.693 C 55.1 78.693 52.255 73.558 52.255 65.389 C 52.255 57.22 55.1 49.109 63.103 49.109 C 71.106 49.109 77.593 55.732 77.593 63.901 Z"
          }
        ]
      ]
    },
    "walk": {
      "animName": "walk",
      "aabb": {"x": 1, "y": 0, "width": 128, "height": 128},
      "frames": [
        [
          {
            "tags": ["leg-l"],
            "style": {
              "fill-opacity": "0.5",
              "stroke": "rgb(0, 0, 0)",
              "stroke-opacity": "0.5",
              "stroke-width": "0.5px",
              "fill": "rgb(85, 85, 85)",
              "pointer-events": "none"
            },
            "tagName": "path",
            "d": "M 61 44.8 L 61 64.2 L 41.569 64.094 L 34.682 60.232 L 34.476 50.851 L 41.464 44.726 L 61 44.8 Z"
          },
          {
            "tags": ["leg-r"],
            "style": {
              "fill-opacity": "0.5",
              "stroke": "rgb(0, 0, 0)",
              "stroke-opacity": "0.5",
              "stroke-width": "0.5px",
              "pointer-events": "none",
              "fill": "rgb(85, 85, 85)"
            },
            "tagName": "path",
            "d": "M 61 63.8 L 61 83.2 L 41.569 83.094 L 41.464 63.726 L 61 63.8 Z"
          },
          {
            "tags": ["arm-l"],
            "style": {
              "stroke": "rgb(0, 0, 0)",
              "stroke-opacity": "0.5",
              "stroke-width": "0.5px",
              "fill": "rgb(0, 0, 255)",
              "pointer-events": "none"
            },
            "tagName": "path",
            "d": "M 74.757 27.592 C 78.488 33.379 74.687 40.059 72.654 40.059 C 70.621 40.059 43.563 45.526 43.563 40.897 C 43.563 38.575 49.41 31.536 53.168 28.766 C 56.903 26.014 62.447 25.498 63.46 25.498 C 64.391 25.498 71.604 22.702 74.757 27.592 Z"
          },
          {
            "tags": ["arm-r"],
            "style": {
              "stroke": "rgb(0, 0, 0)",
              "stroke-opacity": "0.5",
              "stroke-width": "0.5px",
              "fill": "rgb(0, 0, 255)",
              "pointer-events": "none"
            },
            "tagName": "path",
            "d": "M 71.324 98.99 C 75.055 93.203 74.687 86.401 72.654 86.401 C 70.621 86.401 43.563 80.934 43.563 85.563 C 43.563 87.885 49.41 94.924 53.168 97.694 C 56.903 100.446 62.447 100.962 63.46 100.962 C 64.391 100.962 68.171 103.88 71.324 98.99 Z"
          },
          {
            "tags": ["chest"],
            "transform": [
              0.01447,
              0.999895,
              -0.999895,
              0.01447,
              122.663403,
              1.105447
            ],
            "style": {
              "stroke": "rgb(0, 0, 0)",
              "stroke-width": "0.5px",
              "fill-opacity": "0.6",
              "pointer-events": "none"
            },
            "tagName": "path",
            "d": "M 81.223 74.845 C 71.191 83.134 52.524 82.07 42.188 74.162 C 36.114 69.515 34.059 54.043 35.801 52.126 C 41.024 46.378 47.308 45.961 47.308 45.961 C 47.308 45.961 57.222 44.8 62.25 44.981 C 68.007 45.188 79.285 47.902 79.285 47.902 C 79.285 47.902 81.942 48.104 85.3 51.4 C 86.927 52.996 87.338 69.792 81.223 74.845 Z"
          },
          {
            "tags": ["shoulders"],
            "transform": [
              0.996287,
              -0.086089,
              0.086089,
              0.996287,
              -5.241301,
              5.215904
            ],
            "style": {
              "stroke": "rgb(0, 0, 0)",
              "pointer-events": "none",
              "fill-opacity": "0.8"
            },
            "tagName": "path",
            "d": "M 73.097 46.523 C 71.452 48.74 69.296 69.316 70.544 83.678 C 70.727 85.782 71.33 92.218 70.936 94.076 C 69.416 101.242 66.77 102.367 61.961 101.951 C 51.271 101.026 45.097 91.49 41.302 85.286 C 37.507 79.082 42.141 48.337 43.026 44.223 C 44.385 37.907 55.759 24.728 62.914 24.728 C 69.637 24.728 69.336 25.394 73.698 26.976 C 78.032 28.548 74.866 44.139 73.097 46.523 Z"
          },
          {
            "tags": ["head"],
            "transform": [-1, 0, 0, -1, 0, 0],
            "style": {
              "fill-opacity": "0.5",
              "stroke": "rgb(0, 0, 0)",
              "fill": "rgb(244, 212, 255)",
              "stroke-width": "0.25px",
              "pointer-events": "none"
            },
            "tagName": "ellipse",
            "cx": -67.745,
            "cy": -63.901,
            "rx": 14.49,
            "ry": 14.792
          },
          {
            "tags": ["hair"],
            "transform": [-1, 0, 0, -1, 131.848003, 127.802002],
            "style": {
              "fill-opacity": "0.5",
              "stroke": "rgb(0, 0, 0)",
              "stroke-width": "0.25px",
              "pointer-events": "none"
            },
            "tagName": "path",
            "d": "M 78.593 63.901 C 78.593 72.07 72.106 78.693 64.103 78.693 C 56.1 78.693 53.255 73.558 53.255 65.389 C 53.255 57.22 56.1 49.109 64.103 49.109 C 72.106 49.109 78.593 55.732 78.593 63.901 Z"
          }
        ],
        [
          {
            "tags": ["leg-l"],
            "style": {
              "fill-opacity": "0.5",
              "stroke": "rgb(0, 0, 0)",
              "stroke-opacity": "0.5",
              "stroke-width": "0.5px",
              "fill": "rgb(85, 85, 85)",
              "pointer-events": "none"
            },
            "tagName": "path",
            "d": "M 61 44.8 L 61 64.2 L 41.569 64.094 L 34.682 60.232 L 34.476 50.851 L 41.464 44.726 L 61 44.8 Z"
          },
          {
            "tags": ["leg-r"],
            "style": {
              "fill-opacity": "0.5",
              "stroke": "rgb(0, 0, 0)",
              "stroke-opacity": "0.5",
              "stroke-width": "0.5px",
              "pointer-events": "none",
              "fill": "rgb(85, 85, 85)"
            },
            "tagName": "path",
            "d": "M 61 63.8 L 61 83.2 L 41.569 83.094 L 41.464 63.726 L 61 63.8 Z"
          },
          {
            "tags": ["arm-l"],
            "style": {
              "stroke": "rgb(0, 0, 0)",
              "stroke-opacity": "0.5",
              "stroke-width": "0.5px",
              "fill": "rgb(0, 0, 255)",
              "pointer-events": "none"
            },
            "tagName": "path",
            "d": "M 74.757 27.592 C 78.488 33.379 74.687 40.059 72.654 40.059 C 70.621 40.059 43.563 45.526 43.563 40.897 C 43.563 38.575 49.41 31.536 53.168 28.766 C 56.903 26.014 62.447 25.498 63.46 25.498 C 64.391 25.498 71.604 22.702 74.757 27.592 Z"
          },
          {
            "tags": ["arm-r"],
            "style": {
              "stroke": "rgb(0, 0, 0)",
              "stroke-opacity": "0.5",
              "stroke-width": "0.5px",
              "fill": "rgb(0, 0, 255)",
              "pointer-events": "none"
            },
            "tagName": "path",
            "d": "M 71.324 98.99 C 75.055 93.203 74.687 86.401 72.654 86.401 C 70.621 86.401 43.563 80.934 43.563 85.563 C 43.563 87.885 49.41 94.924 53.168 97.694 C 56.903 100.446 62.447 100.962 63.46 100.962 C 64.391 100.962 68.171 103.88 71.324 98.99 Z"
          },
          {
            "tags": ["chest"],
            "transform": [
              0.01447,
              0.999895,
              -0.999895,
              0.01447,
              122.663403,
              1.105447
            ],
            "style": {
              "stroke": "rgb(0, 0, 0)",
              "stroke-width": "0.5px",
              "fill-opacity": "0.6",
              "pointer-events": "none"
            },
            "tagName": "path",
            "d": "M 81.223 74.845 C 71.191 83.134 52.524 82.07 42.188 74.162 C 36.114 69.515 34.059 54.043 35.801 52.126 C 41.024 46.378 47.308 45.961 47.308 45.961 C 47.308 45.961 57.222 44.8 62.25 44.981 C 68.007 45.188 79.285 47.902 79.285 47.902 C 79.285 47.902 81.942 48.104 85.3 51.4 C 86.927 52.996 87.338 69.792 81.223 74.845 Z"
          },
          {
            "tags": ["shoulders"],
            "transform": [
              0.996287,
              -0.086089,
              0.086089,
              0.996287,
              -5.241301,
              5.215904
            ],
            "style": {
              "stroke": "rgb(0, 0, 0)",
              "pointer-events": "none",
              "fill-opacity": "0.8"
            },
            "tagName": "path",
            "d": "M 73.097 46.523 C 71.452 48.74 69.296 69.316 70.544 83.678 C 70.727 85.782 71.33 92.218 70.936 94.076 C 69.416 101.242 66.77 102.367 61.961 101.951 C 51.271 101.026 45.097 91.49 41.302 85.286 C 37.507 79.082 42.141 48.337 43.026 44.223 C 44.385 37.907 55.759 24.728 62.914 24.728 C 69.637 24.728 69.336 25.394 73.698 26.976 C 78.032 28.548 74.866 44.139 73.097 46.523 Z"
          },
          {
            "tags": ["head"],
            "transform": [-1, 0, 0, -1, 0, 0],
            "style": {
              "fill-opacity": "0.5",
              "stroke": "rgb(0, 0, 0)",
              "fill": "rgb(244, 212, 255)",
              "stroke-width": "0.25px",
              "pointer-events": "none"
            },
            "tagName": "ellipse",
            "cx": -67.745,
            "cy": -63.901,
            "rx": 14.49,
            "ry": 14.792
          },
          {
            "tags": ["hair"],
            "transform": [-1, 0, 0, -1, 131.848003, 127.802002],
            "style": {
              "fill-opacity": "0.5",
              "stroke": "rgb(0, 0, 0)",
              "stroke-width": "0.25px",
              "pointer-events": "none"
            },
            "tagName": "path",
            "d": "M 78.593 63.901 C 78.593 72.07 72.106 78.693 64.103 78.693 C 56.1 78.693 53.255 73.558 53.255 65.389 C 53.255 57.22 56.1 49.109 64.103 49.109 C 72.106 49.109 78.593 55.732 78.593 63.901 Z"
          }
        ]
      ]
    }
  },
  "zoom": 2
}